cbook/__init__.py
cbook/__main__.py
cbook/config/__init__.py
cbook/config/config.py
cbook/controller/__init__.py
cbook/controller/mw_controller.py
cbook/controller/rc_controller.py
cbook/controller/re_controller.py
cbook/model/__init__.py
cbook/model/cb_model.py
cbook/model/helper.py
cbook/model/recipe_parser.py
cbook/view/__init__.py
cbook/view/cbook.svg
cbook/view/cbook_rounded.svg
cbook/view/main_window.py
cbook/view/main_window.ui
cbook/view/meal_icon.svg
cbook/view/recipe_button.py
cbook/view/recipe_button.ui
cbook-0.0.4.dist-info/LICENSE
cbook-0.0.4.dist-info/METADATA
cbook-0.0.4.dist-info/WHEEL
cbook-0.0.4.dist-info/entry_points.txt
cbook-0.0.4.dist-info/top_level.txt
cbook-0.0.4.dist-info/RECORD
