Metadata-Version: 2.1
Name: cbook
Version: 0.0.4
Summary: Cookbook app: create, edit, show and filter recipes.
Home-page: https://github.com/br0uQ/cbook
Author: Joshua Schmucker
Author-email: joshua.schmucker@gmail.com
License: GNU GPLv3
Keywords: cbook,recpipes,recipe management
Platform: UNKNOWN
Classifier: Development Status :: 3 - Alpha
Classifier: Environment :: X11 Applications :: Qt
Classifier: Intended Audience :: End Users/Desktop
Classifier: License :: OSI Approved :: GNU General Public License v3 (GPLv3)
Classifier: Natural Language :: German
Classifier: Operating System :: Unix
Classifier: Topic :: Utilities
License-File: LICENSE
Requires-Dist: PyQt5
Requires-Dist: Pillow
